s3synchrony/__init__.py
s3synchrony/s3synchrony.py
s3synchrony/DataPlatforms/__init__.py
s3synchrony/DataPlatforms/baseconn.py
s3synchrony/DataPlatforms/s3conn.py
synchrony-0.1.1.dist-info/COPYING.txt
synchrony-0.1.1.dist-info/LICENSE.md
synchrony-0.1.1.dist-info/METADATA
synchrony-0.1.1.dist-info/WHEEL
synchrony-0.1.1.dist-info/top_level.txt
synchrony-0.1.1.dist-info/RECORD
